optio/__init__.py
optio/parser.py
optio-1.0.0.dist-info/LICENSE.txt
optio-1.0.0.dist-info/METADATA
optio-1.0.0.dist-info/WHEEL
optio-1.0.0.dist-info/top_level.txt
optio-1.0.0.dist-info/RECORD
