Metadata-Version: 2.1
Name: optio
Version: 1.0.0
Summary: Command-line argument parser
Home-page: https://github.com/zhukovdm/optio
Author: Dmitry Zhukov
Author-email: zhukovdm@proton.me
Keywords: argparse,argument parser,option parser,optparse
Classifier: Operating System :: OS Independent
Classifier: Programming Language :: Python :: 3
Classifier: License :: OSI Approved :: MIT License
Requires-Python: >=3.8.0
License-File: LICENSE.txt
